sevdeskapi/__init__.py
sevdeskapi/client.py
sevdeskapi/exception.py
sevdeskapi/controller/__init__.py
sevdeskapi/controller/base.py
sevdeskapi/controller/category.py
sevdeskapi/controller/communication_way.py
sevdeskapi/controller/contact.py
sevdeskapi/controller/contact_address.py
sevdeskapi/controller/country.py
sevdeskapi/controller/document.py
sevdeskapi/controller/feed.py
sevdeskapi/controller/tag.py
sevdeskapi/models/__init__.py
sevdeskapi/models/base.py
sevdeskapi/models/category.py
sevdeskapi/models/communication_way.py
sevdeskapi/models/contact.py
sevdeskapi/models/contact_address.py
sevdeskapi/models/country.py
sevdeskapi/models/document.py
sevdeskapi/models/feed.py
sevdeskapi/models/tag.py
sevdeskapi/test/__init__.py
sevdeskapi/test/test_contact.py
sevdeskapi/utils/__init__.py
sevdeskapi/utils/converter.py
sevdeskapi/utils/map.py
sevdeskapi/utils/queryset.py
sevdeskapi/utils/sevdeskfield.py
sevdeskapi-0.2.0.dist-info/LICENSE
sevdeskapi-0.2.0.dist-info/METADATA
sevdeskapi-0.2.0.dist-info/WHEEL
sevdeskapi-0.2.0.dist-info/top_level.txt
sevdeskapi-0.2.0.dist-info/RECORD
